4-bit-shift-register/rtl/shift_register_4bit.v
module shift_register_4bit (
    input wire clk,
    input wire rst,
    input wire serial_in,
    output reg [3:0] q
);

always @(posedge clk or posedge rst) begin
    if(rst)
        q <= 4'b0000;
    else
        q <= {q[2:0],serial_in};
end

endmodule

4-bit-shift-register/tb/shift_register_4bit_tb.v
`timescale 1ns/1ps

module shift_register_4bit_tb;

    reg clk;
    reg rst;
    reg serial_in;
    wire [3:0] q;

    // Instantiate the shift register
    shift_register_4bit dut (
        .clk(clk),
        .rst(rst),
        .serial_in(serial_in),
        .q(q)
    );

    // Clock generation
    always #5 clk = ~clk;

    initial begin
        $dumpfile("sim/waveform.vcd");
        $dumpvars(0, shift_register_4bit_tb);
    end


    // Test sequence
    initial begin

        // Initial values
        clk = 0;
        rst = 1;
        serial_in = 0;

        // Reset the shift register
        #10;
        rst = 0;

        // Shift in 1
        serial_in = 1;
        #10;

        // Shift in 0
        serial_in = 0;
        #10;

        // Shift in 1
        serial_in = 1;
        #10;

        // Shift in 1
        serial_in = 1;
        #10;

        // End simulation
        $finish;
    end

    // Display signals in terminal
    initial begin
        $monitor("Time: %0t | clk: %b | rst: %b | serial_in: %b | q: %b",
                 $time, clk, rst, serial_in, q);
    end

endmodule

4-bit-shift-register/sim/waveform.vcd
$date
	Mon Oct 05 20:00:04 2026
$end
$version
	Icarus Verilog
$end
$timescale
	1ps
$end
$scope module shift_register_4bit_tb $end
$var wire 4 ! q [3:0] $end
$var reg 1 " clk $end
$var reg 1 # rst $end
$var reg 1 $ serial_in $end
$scope module dut $end
$var wire 1 " clk $end
$var wire 1 # rst $end
$var wire 1 $ serial_in $end
$var reg 4 % q [3:0] $end
$upscope $end
$upscope $end
$enddefinitions $end
$comment Show the parameter values. $end
$dumpall
$end
#0
$dumpvars
b0 %
0$
1#
0"
b0 !
$end
#5000
1"
#10000
0"
1$
0#
#15000
b1 !
b1 %
1"
#20000
0"
0$
#25000
b10 !
b10 %
1"
#30000
0"
1$
#35000
b101 !
b101 %
1"
#40000
0"
#45000
b1011 !
b1011 %
1"
